runscript/__init__.py
runscript/__main__.py
script_runner-0.2.3.dist-info/METADATA
script_runner-0.2.3.dist-info/RECORD
script_runner-0.2.3.dist-info/WHEEL
script_runner-0.2.3.dist-info/entry_points.txt
script_runner-0.2.3.dist-info/top_level.txt
