Metadata-Version: 1.1
Name: script-runner
Version: 0.2.3
Summary: A wrapper for running scripts
Home-page: https://github.com/kaniblu/script-runner
Author: Kang Min Yoo
Author-email: kaniblurous@gmail.com
License: GPL
Platform: Operating System :: MacOS :: MacOS X
Platform: Operating System :: POSIX :: Linux
Classifier: Environment :: Console
Classifier: Intended Audience :: Developers
Classifier: Programming Language :: Java
Classifier: Programming Language :: Python
